MANIFEST.in
README.md
main.py
requirements.txt
setup.py
dev_gpt/__init__.py
dev_gpt/cli.py
dev_gpt/constants.py
dev_gpt/env.py
dev_gpt.egg-info/PKG-INFO
dev_gpt.egg-info/SOURCES.txt
dev_gpt.egg-info/dependency_links.txt
dev_gpt.egg-info/entry_points.txt
dev_gpt.egg-info/requires.txt
dev_gpt.egg-info/top_level.txt
dev_gpt/apis/__init__.py
dev_gpt/apis/gpt.py
dev_gpt/apis/jina_cloud.py
dev_gpt/apis/pypi.py
dev_gpt/options/__init__.py
dev_gpt/options/configure/__init__.py
dev_gpt/options/configure/key_handling.py
dev_gpt/options/deploy/__init__.py
dev_gpt/options/deploy/deployer.py
dev_gpt/options/generate/__init__.py
dev_gpt/options/generate/conversation_logger.py
dev_gpt/options/generate/generator.py
dev_gpt/options/generate/parser.py
dev_gpt/options/generate/prompt_factory.py
dev_gpt/options/generate/templates_system.py
dev_gpt/options/generate/templates_user.py
dev_gpt/options/generate/ui.py
dev_gpt/options/generate/chains/__init__.py
dev_gpt/options/generate/chains/auto_refine_description.py
dev_gpt/options/generate/chains/extract_information.py
dev_gpt/options/generate/chains/fix_based_on_error.py
dev_gpt/options/generate/chains/get_user_input_if_needed.py
dev_gpt/options/generate/chains/question_answering.py
dev_gpt/options/generate/chains/translation.py
dev_gpt/options/generate/chains/user_confirmation_feedback_loop.py
dev_gpt/options/generate/pm/__init__.py
dev_gpt/options/generate/pm/pm.py
dev_gpt/options/generate/pm/task_tree_schema.py
dev_gpt/options/generate/static_files/base_image/Dockerfile
dev_gpt/options/generate/static_files/gateway/Dockerfile
dev_gpt/options/generate/static_files/gateway/__init__.py
dev_gpt/options/generate/static_files/gateway/app_config.toml
dev_gpt/options/generate/static_files/gateway/app_template.py
dev_gpt/options/generate/static_files/gateway/custom_gateway.py
dev_gpt/options/generate/static_files/gateway/nginx.conf
dev_gpt/options/generate/static_files/gateway/requirements.txt
dev_gpt/options/generate/static_files/microservice/Dockerfile
dev_gpt/options/generate/static_files/microservice/__init__.py
dev_gpt/options/generate/static_files/microservice/google_custom_search.py
