Metadata-Version: 2.1
Name: dev-gpt
Version: 0.18.43
Summary: Use natural language interface to generate, deploy and update your microservice infrastructure.
Home-page: https://github.com/jina-ai/dev-gpt
Author: Jina AI
Author-email: hello@jina.ai
License: Apache 2.0
Platform: UNKNOWN
Classifier: Development Status :: 3 - Alpha
Classifier: Intended Audience :: Developers
Classifier: License :: OSI Approved :: Apache Software License
Classifier: Programming Language :: Python :: 3
Classifier: Programming Language :: Python :: 3.8
Classifier: Programming Language :: Python :: 3.9
Classifier: Programming Language :: Python :: 3.10
Classifier: Programming Language :: Python :: 3.11
